django_swiftapi/__init__.py
django_swiftapi/dynamic_environment.py
django_swiftapi/exceptions.py
django_swiftapi/crud_operation/__init__.py
django_swiftapi/crud_operation/core.py
django_swiftapi/crud_operation/file_operations/__init__.py
django_swiftapi/crud_operation/file_operations/files_handlers.py
django_swiftapi/crud_operation/file_operations/files_validators.py
django_swiftapi/crud_operation/file_operations/storage_operations/__init__.py
django_swiftapi/crud_operation/file_operations/storage_operations/aws_s3.py
django_swiftapi/crud_operation/file_operations/storage_operations/base.py
django_swiftapi/crud_operation/file_operations/storage_operations/local.py
django_swiftapi/crud_operation/file_operations/storage_operations/utils/__init__.py
django_swiftapi/crud_operation/file_operations/storage_operations/utils/aws_s3.py
django_swiftapi/modelcontrol/__init__.py
django_swiftapi/modelcontrol/authenticators/__init__.py
django_swiftapi/modelcontrol/authenticators/base.py
django_swiftapi/modelcontrol/authenticators/django_allauth.py
django_swiftapi/modelcontrol/modelcontrollers/__init__.py
django_swiftapi/modelcontrol/modelcontrollers/base.py
django_swiftapi/modelcontrol/models/__init__.py
django_swiftapi/modelcontrol/models/base.py
django_swiftapi/modelcontrol/schemas/__init__.py
django_swiftapi/modelcontrol/schemas/base.py
django_swiftapi-0.1.15.dist-info/licenses/LICENSE
django_swiftapi-0.1.15.dist-info/METADATA
django_swiftapi-0.1.15.dist-info/WHEEL
django_swiftapi-0.1.15.dist-info/top_level.txt
django_swiftapi-0.1.15.dist-info/RECORD
