Metadata-Version: 2.4
Name: django_swiftapi
Version: 0.1.15
Summary: Easy to use django package for building APIs quicker than ever, built on top of django-ninja-extra
Home-page: https://github.com/deepdiverguy/django_swiftapi
Author: Md Sohanur Khan Sagor
Author-email: guy04473@gmail.com
License: MIT
Classifier: Programming Language :: Python :: 3
Classifier: Operating System :: OS Independent
Requires-Python: >=3.7
License-File: LICENSE
Requires-Dist: django
Requires-Dist: django-ninja
Requires-Dist: ninja-schema
Requires-Dist: django-ninja-extra
Requires-Dist: asgiref
Requires-Dist: Pillow
Dynamic: author
Dynamic: author-email
Dynamic: classifier
Dynamic: description
Dynamic: description-content-type
Dynamic: home-page
Dynamic: license
Dynamic: license-file
Dynamic: requires-dist
Dynamic: requires-python
Dynamic: summary
